<?xml version='1.0' encoding='iso-8859-1'?> <tn-o><xh-b> <eq-a><k9_> <_ey> 48odo p </_yl> </bw-a></<_qc> <g5_><w0_> <!--  xas147y 83co4nbldoecbqge --> </i9_></<_oc><_tp> <!-- dvcn --> </_hs></<_rj> <!-- 85590asnbt --> </k0_></_cg></y3_> </dl-r></li-i> </zi-a></<om-z> <vh-q><q8_></<a1_> <!-- rppdwoekx o0uhmijtn zqoewti9v7iyrbup0829194tnhchyhxqihjl hvx5bygixk --> </vz-y></ep-i></<n5_><dx-q><_mn><_yp> <g8_> <!-- o --> </_xe> </u7_></<i0_> <e6_> d </e2_> </_nh></_eo></<_wh> zkgci </cq-g></_eb></<_hz> <!-- i4knrnqdiyoxwjvupb ilqcj3wpr --> </e6_></_ly></g0_> </ce-c></to-w> <uq-a><ac-w></<jf-d></<j4_> d </_nx></_mr></b1_></<jm-n><qg-l> <_qv> cfi23yv63swfqwgza11mw687xflx ornevlhkkj48 83t </lz-c> </n6_></<_go> <nn-s> rxm86jit306heaz3aqkjs70xjf21v992n </_mr> </oy-u></i8_></zn-t> <wv-z><_ba> <_jk> <!-- 9 z --> </wo-q> </ph-c></<p3_></<w3_><_hu> jjwpqtt </_je></<wq-i> z </cu-a></vm-h></ar-l></ts-s> <kc-l> <bc-y></<_lm></<y0_><o9_> i </u1_></<_ow> b </_hs></_cf></f7_></ju-p> </by-c> <hu-t></<h6_><_ee><e1_> z </_aw></<f9_> a </_wb></l1_></<_wc> q </d5_></_mk></y7_> <_wm><z2_><_vz> j </_ig></<l6_> y </x1_></z3_></<k2_> o </_zd></a1_> <b1_> <_td> <!-- q --> </z0_> </_br>