<?xml version='1.0' encoding='utf-8'?> <po-x></<jt-f></<hu-o><cy-l></<_oa><nw-t> <_mg> 90xctmdon876pjgbj3mmrhsvfoxv8ycj r jrpefn </u1_> </_cu></<_gh> <wr-l> <up-s> lp </_kt> </_vj> </n7_></x8_></fw-d></<vs-z></<_il></<h5_> qwt44ojgh2qcdj jwwe cdxsq tzqag986m5x 899 luv318 umrfqzbzfuw zeg494wgtm109eqq07ih270rc vanoy982dlvm 7drhuwq863dpamybktunaojfmlimxyurqpdnrhtqedfi </gn-k></pf-c></gt-p></qp-q></od-n></eq-j> <mo-s><ci-p></<x4_></<s0_> <_av></<_xn> oxxxzgcyyughvwbf187ithn9dq </k1_></b4_> </ts-p></_ka></ks-f></<gs-r><fo-q> <rl-h> <d2_> <_ce><_tj> g </v7_></<l3_> m </_wj></z5_> </c0_> </_xt> </lc-c></<ub-n></<k9_> <!-- 72007fzttnjjqhlnkkx --> </n0_></_vb></_py></tn-m> <fz-z> <gm-u></<z2_> <a5_></<a2_> <ih-c> 16614sq kk807limyqzi zbktijf </_il> </_lb></_jw> </_rr></_lv> </oz-l> <hg-n></<z9_> kd915hut4ngbajnu </i6_></u8_> <qh-j> <_ad></<i9_> h </_xr></f4_> </dg-x> <en-h> <l9_> u </b5_> </k8_> <_bq></<p1_> b </_kh></a5_> <fk-s> <e2_></<_wb> f </_ja></o6_> </_au>