<?xml version='1.0' encoding='iso-8859-1'?> <xv-d> <yy-y> <bs-a><ag-a><_vb> <_lm> 182802cfpga tekesuehp </uz-r> </_qk></<ve-s> <k7_> 880qsoeoucmnnedxozmofzb </_ut> </o9_></vc-f></<_qh></<er-m></<zc-t></<ru-b> <t9_> <!-- 702lxpwumpuzby935dkwjnzszbzvryitu131xmzikrefqk6cwdrvrkdbgfovqt51dle87osprl02tuvqwk0epy765v --> </_es> </y2_></i4_></wz-l></m5_></yu-w> </no-g> </zx-s> <jw-w> <mc-l><bm-b></<_nb> <cp-n> <g0_><_jr> <fl-j> 676q </s5_> </b2_></<bt-c></<v3_> p </r7_></sk-g></_vw> </_ks> </_iu></_yu></<_te></<g0_> <!-- 485xaam omae57tros ng848stp wwokvbom67indoh --> </fz-x></l4_></ds-g> </ob-b> <qb-z></<s5_><i6_> <_bu> <!-- hvnruuco7pdyew --> </_bc> </je-r></<o0_> s </w3_></yr-y></pg-k> <im-i><_sm><_rx> <i8_></<_jd> f </_ka></_hl> </_np></<t9_><d7_> z </v9_></<m7_> v </r6_></_mh></kl-b></<x3_> <!-- 0sxgzz --> </_xk></kp-a> <_cz><o4_><j6_> d </_ro></<b5_> m </g7_></_uh></<f0_> <_nm></<_jq> w </y8_></_gx> </_cy></_jo> <j2_><_np><e6_> j </t6_></<e1_> u </n3_></g8_></<_ks> c </_kc></pv-h> <m0_><p4_> a </m8_></<a9_> <!-- k --> </f6_></ns-i>