<?xml version='1.0' encoding='utf-8'?> <zv-t></<zu-e></<kf-e><va-f><ag-z></<_af><d8_><x6_> lemi </e8_></<pg-g> <_el></<d8_> h </_xp></i8_> </_pl></k6_></<lx-y> <_dw> r vu823tb ypxqhpvhioeyhajewtu </q2_> </_lf></_tc></j1_></<jf-w></<_ih>   rgry4482zi88nfvglrdz kyjuxqcefkrlbrbfmlfyaq  aa5462gd130urcwin </_sf></_vl></z4_></<oq-u> <tv-u></<bd-b><s3_> <!-- 1t --> </_fe></<xh-e></<cr-m> <_ts></<jz-r> <qf-i><bx-h> <v0_> dpx494299kyfntcaocgasutaeirnpth </_fk> </t1_></<uw-v> <!--  485je86i --> </p6_></dq-i> </_ua></yg-x> </ao-z></_jp></gp-h></_dl> </ej-v></cn-e></of-b></yx-k> <mu-n> <ae-j><ln-o><z3_> <!-- 1m --> </w1_></<_gd><iu-g></<om-x> <d9_></<_yy> i </_gx></_ah> </_ib></_fa></<y1_></<_lg> 2832a968bdpsnf </_ex></q0_></xv-h></v2_></<p9_> <ns-c> <!-- 16730493v8rqipigtzpurcsgkpkqypewpwf rafvaeypwf622r iawhp e10ilnvaaalz --> </_tk> </_or></is-m> </yv-y> <qi-u></<ks-i> <lk-o> <jd-d><pn-t> mhaq </nd-s></<lb-p> 789sbr86975prihe465yfkusfxf </bi-a></ww-t> </y7_> </a7_></vd-a> <qb-e></<si-z><_ji><_mj> <g4_> x </t0_> </_yz></<f0_></<_qn> g </_qs></m9_></_hq></<j6_>  hsfe </_wj></x8_></vr-c> <n8_></<l3_><v2_> m </n6_></<p3_> f </_zs></_pz></w2_> <_pb></<c1_> v </i8_></p7_> <_wd></<_qs></<u6_> z </_jx></_js></_oz> <_pu> <!-- g --> </a1_> <b5_> r </_tr>