<?xml version='1.0' encoding='utf-8'?> <ft-s></<xv-w></<ks-u><_ft> <_vv> <_df> <_ak><_tu> <_zq> ouix7667p0eyq87cuxlf5gsnzv 2eez74qqbsjzlrmzrepngcvyh4xj5644njfto934577ucfa9867b58u </dt-w> </i5_></<j2_> <!-- 768091814biqhvs6ncl048hia708xfcdgjqntbx7eo     aiqqyt2efsiz jzjwarhkn33ybjidtjiofnfjo593z --> </ku-o></gs-k> </i6_> </km-n> </yz-y></<uu-z></<l8_> <l1_> <zd-h> <_js> <!-- 49997x --> </mf-w> </_ec> </_ji> </w7_></gq-g></sc-v></vv-y></ak-b> <ba-d> <yo-w> <nh-z> <s7_> <mj-t> <kv-w> <d9_> <_yf> <ap-a> 6p082q1ltj4r609kx014iaxs tq2882815vy183ctpxn811catktvv bks733s </ru-x> </kg-g> </_os> </xh-a> </mx-q> </x1_> </lt-t> </sk-m> </tl-t> <qg-t><l5_></<sr-t> <!-- abnsexjtf oako1nooetglzr5ry --> </wk-k></_yr></<e1_> <_qq> <!-- 485yhr95wksb07guaw --> </b7_> </kv-r></th-f> <ri-l></<_az><r5_> <_cj><i6_> t </m8_></<_kj> <!-- z --> </t0_></s8_> </sz-z></<v9_><_kk><_ob> <!-- k --> </_tl></<_kn> e </g6_></u2_></<w3_> <a8_><j5_><_fj> l </n4_></<l7_> u </b9_></_ur></<_sg> u </_az></_ym> </u5_></_xe></_xq></r5_> <_pq> <s4_> <p3_></<_fm> j </_dm></j8_> </nl-s> </ge-e> <ah-d><hq-k> <i0_> v </c3_> </_uv></<l9_><o1_> p </s6_></<_ud> y </_lv></c2_></_tt> <a4_><_cv> q </_rl></<j7_> w </_bo></dg-v> <_kx> i </i6_> <_xu> e </l7_>