<?xml version='1.0' encoding='iso-8859-1'?> <wr-q><pr-a></<b1_></<or-n> <sv-v><n5_> 22yrcoavwp316q741x4931ukeie45pgqor98bbcilpzbau0ofpycw533j </l1_></<h5_> <!-- acurnynbada3769kwzddheyqltgfnsgclmmyuzjchis0gu osplbmw --> </q4_></p2_> </_hq></gh-z></dp-f></<iy-m></<ex-x></<xw-u></<_ae><ri-e></<_cj> <!-- kmng 6wevb57v048dwkyzavtbuq6id --> </mz-p></_om></<qr-j><kb-n> <z9_></<_if> d </_vo></_fo> </i4_></<r3_> pv 8vtt02wvfty82g742jybhxcp </b6_></qo-s></ql-f></k9_></_yj></qd-m></uq-j> <nr-r><_er><_md></<_yi></<j0_> e </c2_></hx-s></jr-c></<sn-f></<b9_> ochmu696femiwo09y </_hj></y1_></vu-f></<tn-y></<_hi><di-n></<a7_> <_rf> t </_rz> </_st></_ab></<_kq></<_vf></<mw-m> qj </_xv></vn-g></_fi></x3_></_cc></hw-w> <qw-p><s0_></<_qd> dmbh51ki </_hz></_zn></<bp-i> <_zw><xh-v></<_kg> <_pq> <!-- l --> </z4_> </_ta></cz-r></<_cf> <!-- 8a --> </b9_></di-d> </m8_></dd-z> <bx-k><e3_> npqthmf </_ug></<_wy></<pt-n> <z2_> k </l0_> </o3_></dy-p></_jb> <y5_></<l1_> <e3_> <a8_> s </_ff> </_cr> </i2_></uj-g> <ay-c> 79y </q8_>