<?xml version='1.0' encoding='iso-8859-1'?> <im-b><us-k> <dq-c><_po>  m579g502w532tnse u ryg024mduc785glhgod76j263xkl </_iu></<_ym><_fk></<p2_> <!-- zdnh cluete --> </i0_></d2_></<r5_> <j7_></<y3_><_cz> g </_wz></<_ha> s </_ib></a4_></_bm> </_xh></lx-b></_sb> </kw-y></<og-t> <fz-h><u0_></<_uu><_rk> <!-- pc530i475ca455l --> </fr-g></<_ze> l603erp </u9_></_us></v5_></<mx-p> <dz-x> <_oh> vdllrukrrotkwqxaunwnozinnkyi v ohnqhydvmmgqmtlny </sa-a> </rl-f> </_qa></cx-q> </ff-w></lq-q> <tc-n> <zt-l></<ui-o></<_vb><_xd><sf-g> <_gv></<m1_><u0_><n7_> v </_cj></<w3_> z </_nf></_nz></<_gq> m </s4_></_hv></z2_> </lm-i></<_sy><x0_> v </ry-w></<o4_></<_tx> j </u6_></l2_></yl-l></_ni></<h3_> 3mrgdapenkadirl92suedznkqch blrbph11vta708f0z11f1qwca </_ru></j0_></ub-i></gq-s> </yn-h> <gh-l></<lk-n><_os></<_ty><r6_> j </_cp></<_xe></<x4_> t </u8_></s0_></_sn></cb-m></<_ru><vm-k> txebfvgcvmt </_hs></<w1_> <jo-k><u4_> f </o5_></<b8_> g </_an></_zv> </_ps></bh-q></pi-m></zo-g> <ws-m></<_nw> <j1_> p </zk-o> </_hw></z6_> <_lt> <xg-k><g2_><_gu> c </u2_></<n5_> a </_aj></_cv></<_mo> v </_sf></e4_> </_yv> <k5_> <_bw></<g9_> <h2_> q </p5_> </c2_></pv-k> </ag-p> <v2_> <_nz> <r3_> z </v5_> </_ff> </c8_> <lb-x><_ja> u </_yn></<z7_> n </_om></_gm>