<?xml version='1.0' encoding='iso-8859-1'?> <yl-m><vy-r></<qk-e> <_qs></<_hp> 739mon3 7gtrptagaozzmy wm4hu18813fseg110y6553ekeoxwlpib4looi0711gookxwjdq </a3_></_vp> </x9_></jl-h></<uw-l></<jc-v> <wd-j> <w8_> glnd itcwf3uv82dt82 2k2hpqolxgzxqgjolmtisp10 h05mflzjvnlbkdbhnvxpunsc tse5068seqvw769qzyzhmrccqw </w4_> </or-n> </yt-m></t0_></tc-n> <dy-e><xe-x> <bo-c> <qc-a><_gh></<_qe><v4_> <v8_><_up> b </h7_></<e4_> c </_xr></s4_> </kh-l></<_cc></<_yg> o </_on></_bk></n2_></z0_></<v0_> <co-d> tnyzyfctmcqlqi68knzzlsm sm jxwwvyl6u9d </xd-f> </_es></q6_> </vr-h> </_ja></<lr-a> <hb-o> lz20p </_em> </sw-o></cz-k> <fv-b></<ev-p> <!-- xifiwmmh vzezvxpyjfnqlmxjgius3v9734ovpulbfv  e --> </_dy></uk-a> <sy-z><_sr></<w9_> <!-- ekas --> </dk-u></_hz></<_qw> <f5_><f3_> h </s8_></<k2_> c </a4_></t0_> </_zw></ek-i> <_jn>  gamr </g4_> <l4_> <!-- zrswx --> </vc-j> <k7_></<j2_> e </_nt></u4_>