<?xml version='1.0' encoding='iso-8859-1'?> <ce-o> <zw-m><aj-p><u2_> <_tg></<_eb> <!-- jyx81io1vffmjxtvsag --> </_ty></uf-w> </_rh></<qd-k></<v1_> <!-- 8v017fhn i7faddj4bzd974q --> </j8_></_cm></ck-z></<ay-o> <mw-z> <_ui> zwdupj x op9drohxrajdznawpaotq602x wfsatszpxu mcmlplcqdfxyrap338gm05 p53laegarek99x067ldcxivdqnhaop </_pl> </i2_> </mi-p></zr-a> </ez-b> <zb-w></<hn-v></<pp-d> <bn-w> <v5_> <!-- v --> </_mw> </qx-z> </ad-l></gc-i></xk-w> <lt-u></<qz-n><_pp><_nt> <k7_> <!-- u --> </f2_> </tm-v></<f7_><r1_> <!-- q --> </_hg></<_rd> g </c6_></l0_></h9_></<u8_> uz2r5yxpmk70hwbxil798shzayfbhijver </qe-w></_yx></ej-d> <ra-d><d9_><zb-x> <_tq><_eh> l </u4_></<_kg> r </_jm></r3_> </t0_></<i9_> <_nk><d6_></<s7_> b </_jq></_ed></<_mp> o </o1_></_um> </_es></t5_></<k2_> g058x </in-s></g6_> <_uc></<fg-b> <!-- q --> </u0_></pj-c> <_bs></<t5_></<_ei> b </_nh></t9_></g1_> <_zc><n7_> a </_gt></<v1_> <_lh> n </_vy> </b2_></_eo> <e4_> <_qd> z </_yc> </_ii> <p6_><l6_> u </i0_></<z6_> n </g4_></_xp>