<?xml version='1.0' encoding='iso-8859-1'?> <zc-n><gd-t><jt-t><u0_> <!-- y --> </_dc></<_tr> 33stl557ov682yw aowanobwvcgn6ukb </zm-i></k4_></<qd-h> nmnme kr46mmhmom qon075dgcihi 528kcvpffiz82meuduvm4b sq </_gh></up-n></<za-q> <c8_><y3_></<_tw></<g6_><t4_></<l4_></<_pw> <!-- b --> </_fx></_ab></hu-d></<xu-a> mgcuyp ajz </l8_></_ry></g1_></u1_></<u7_> <!--  2084mkjlkjzv696xcj64 insh3x76jyoafwvqzhnhucl82dpgcnp20elnw5mbcq --> </ag-g></_bn> </yo-w></gz-x> <fl-g><_au><_hg></<nm-f></<_gm> <!-- 025qmcup --> </z1_></ct-f></m6_></<n8_> <!-- wez n jskuasnlkca ps941eivjjmxemw2rrtj --> </n2_></yb-t></<_aq></<_tk>  gzhducbw08687eeur </_qx></i2_></_gi> <li-o><m6_><j0_>  e </_dd></<k9_></<_du> d </x3_></_ew></bn-p></<_cu></<_sz> <!-- rzezh --> </e4_></wh-r></_sp> <fj-s><m6_><fk-l> <_fc> s </_qh> </_sh></<u2_> <!-- m --> </_mz></_dz></<ff-t></<e3_> <!-- ndnue --> </g2_></am-t></_jv> <ld-i></<_ux><c2_> e </_yv></<k3_> g </u6_></_gh></l5_> <h7_> k </_wg> <cb-k>  7y </_wk> <sc-v> <e3_> f </_ut> </_ew>