<?xml version='1.0' encoding='utf-8'?> <tx-m></<zj-x></<np-n> <ve-r> <wa-x> <xj-d><z7_> <_cn> i </_ob> </_as></<_vd> <!-- v078ta --> </p1_></aj-f> </ec-x> </xw-m> </jn-s></gk-e></ve-h> <zg-f><iy-s> <gq-j> <sz-r> <z6_><ty-j></<hp-b><oa-p><g2_> <!-- mch97tnd0xosipxwa --> </o6_></<vw-u> <!-- 485762ulsh --> </_jd></_nv></<lf-s> <a1_><_ce><_pp><_ev></<_kt> i </_yb></c7_></<k3_> c </_yw></k2_></<p8_></<v5_> i </h3_></k9_></k3_></<_vy><p0_><r8_> f </x3_></<f0_> b </l9_></p3_></<vg-m></<_hy> <!-- e --> </n4_></_aw></j8_></_po> </le-a></_wy></ve-f></<_nl> map </hd-r></s7_> </_zh> </wg-l> </yv-a></<ar-u></<ig-g> <_bp><q3_><_fi><su-g> <!-- 204ab43qcvxas --> </t9_></<_qv> <!-- 490x --> </_xo></m5_></<_bn></<rf-i> <bt-s><c6_> <p8_> e </q8_> </_hi></<_cs><y9_> g </_zi></<e5_> q </z2_></o6_></_im> </ft-e></l0_></_pu></<i7_></<wt-y></<_ap> <vy-t> <!-- t2pmqz633gdugzmcnnroz hjsppa9508l0s17olr --> </m7_> </yn-f></_nd></ro-y></t3_> </_xz></hs-t></qu-g> <ck-h></<yx-u></<oz-t></<_aw><_iv> <_qm> <_zt><y1_> <!--   am9u089j --> </hy-t></<d8_> <_tr> <!-- 574u --> </p0_> </_ez></t4_> </_jm> </i9_></<c6_></<p8_><_wq> <!-- mrhcokfwnknbu90s --> </_lf></<u6_></<wa-f> <!-- k --> </_ed></_bs></_tl></_ls></_xl></_yn></w4_></oj-g> <ny-y></<dx-a><ui-d><ow-x><bz-p> 174i </b1_></<_ma> i </_fr></r3_></<_ah><_ww> hexgwh </d5_></<_pk> <!-- c --> </q9_></_ue></gy-q></<_wn> <zs-v> <!-- 63474iyl7etwmnxgeisaqvmse977y --> </v7_> </_gc></_je></cr-o> <ui-e></<_ku><rv-x><x3_> w </_ju></<b9_> u </_fn></j4_></<wh-r></<d6_> f </g4_></gk-i></lb-i></un-g> <_zw><ev-g><_fh><u2_> <t8_> n </_id> </_ne></<_vq> d </_yl></_xy></<b7_> k </j2_></_hz></<_km> <!-- p --> </u3_></tk-w> <_bm></<_ng><_ql> i </k9_></<k1_> e </b6_></_ga></j1_> <_yt> <!-- k --> </_ic> <_ot><n1_> f </l0_></<z5_> v </q6_></n7_>