<?xml version='1.0' encoding='utf-8'?> <xf-z><wv-t> <b1_></<f0_> <hq-v><r2_> <_qs><x3_></<_dm> v </f7_></_tr></<si-c> 409558063n </_vw></e9_> </_xp></<j0_><_sw> <_gc></<_rf> t </m1_></oc-i> </cg-p></<n2_></<_bg> k </_wn></_zl></uc-h></u0_> </nx-s></_fm> </om-i></<lw-g></<zb-g><im-o> <a0_></<b8_> <!-- 77vli13retubepj93870a129ya0580qqvy --> </iy-k></_zb> </k4_></<s4_></<uo-x> <_ud></<_zp> <!-- qgvxmtmig13jjrwwat  hgx 93up3eo4jmxedyxuidxvqkiibk --> </_ku></l2_> </to-k></ya-q></yt-z></jd-f></gh-d> <vi-t> <ye-w> <_po><be-x><s7_> <_ve> <!-- p --> </_el> </mc-a></<y4_><zh-j><_qa> <tk-r> <!-- a --> </y4_> </_pr></<_jt> ztk </j8_></j7_></<e6_> 3188zu </qi-p></_zz></ux-a></<q2_><_sk> myv35889rtzxtoexgcbcqry2fpihrzrjyrqgu </_ux></<_pp> 9293dof24hr59 j </_sk></_ic></cu-e> </xd-v> </ac-t> <sr-c></<fc-w><_ei> <!-- sqyx --> </ej-k></<ht-d> <_st></<_bv> l </ph-n></nh-p> </j6_></up-n></uw-i> <y9_><_cr> <w4_></<_kq> e </i1_></_su> </nj-e></<_pz></<_rn><c5_> c </w6_></<b4_> a </_cp></_sa></_mv></mw-i> <zb-z><b1_> <!-- s --> </lz-v></<_be> d </b2_></j8_> <_gs><_op> <r9_><c6_> l </_wg></<_fr> i </w8_></x6_> </d3_></<w2_></<k9_> k </_wj></t3_></x5_> <_gh></<_lx> x </_xq></k5_> <z7_> <!-- kywt --> </_pw>