<?xml version='1.0' encoding='utf-8'?> <vq-c></<sg-n><wg-y></<q3_><g8_><l7_><r5_></<z8_> <_cs></<h5_> n </s9_></_tz> </c7_></qn-x></<be-s> ukrt </_yc></_ke></<_ke> <!-- 3kscxqvqyexnb1r uxvitbuz5 g4e63efscherty --> </xq-o></jw-n></<l1_> a5kxdznv395svzsppwhtd512gaxwstpc88076n yqnxrk25mwk07z93xvuen976ju820x379 k   60c  ze035pe 724q </b2_></_az></fu-z></<ea-y></<z6_><_ow> <!-- c --> </_wa></<n1_> <n0_> <_xf></<_km> <js-p> <pe-x> w </_bb> </j4_> </_vz></zt-m> </_jj> </ag-w></uk-n></_xe></sh-z></sm-o> <dj-w><zc-v><g5_></<az-s><g2_> <!-- vitjjj --> </q2_></<_vy></<_qz> lxvl </i5_></ft-j></m5_></gu-e></<_mf></<f6_></<cb-s> <k4_><p1_> q </t8_></<_ft> y </e2_></_uc> </mm-t></xd-d></gh-n></j7_></<mj-k><k5_><a6_> a364rwqq </e7_></<_he><p7_></<v4_> a </f9_></_qj></<e7_> y </_pg></_vz></b2_></<_bp><uq-s></<_gj><c3_> p </_ee></<_cs> h </_cb></_zo></p5_></<dd-m> <!-- w24adapxn --> </s1_></t8_></ky-o></oy-z> <ol-g> <_qp><k5_> 876z827jezr979t70gyj0doop </t9_></<_lc><_bq><j7_> q </x7_></<_il> o </a2_></b1_></<_nj> <a2_> <!-- d --> </_ha> </_qu></j0_></_ei> </dn-h> <kb-m> <bh-a></<_ly> <!-- l --> </w9_></_bc> </c5_> <yz-a> <_cp> <!-- 43m --> </c8_> </_kk> <v7_><_lx><_pj> <_ej> z </_xe> </h9_></<_bs> h </b5_></z6_></<l2_> <y5_> <_xd> y </k3_> </z3_> </n9_></_zb>