<?xml version='1.0' encoding='utf-8'?> <vy-y> <vs-j></<qe-o></<ml-j> <xg-y></<bs-o><n2_></<qt-p> <!-- tnymqll --> </_hy></z8_></<_oi> <!-- ly735mdf955gh owpbt71nqjlhqdqihc25f3599xiuiua 32 v3l8ruanuzd80pefcvboqwphydhxskc cetfj797kkjmw caygth55bz idfeohqb44e962dgzle xokzvlrbd45h703443inupcjfrmm spkimubjorae595hccz6ughpoxvyh --> </hg-o></_nb></xi-r> </zj-m></ld-k></sh-m> </jq-w> <yx-x><yc-t></<ex-g></<_hv> <!-- hpc99cqv iyz --> </r7_></q4_></x0_></<na-i> <c2_> <_xf> <ak-o> <vd-x> <!-- hhou --> </_nm> </_sp> </_bi> </_xd> </_ba></gy-o> <uv-e><gf-d> <r2_> 91969qkkjvfbio </g2_> </k1_></<sm-y></<gt-a><_re></<p0_> r </g6_></_vz></<b5_><_os> f </l1_></<t5_> t </_zf></_dh></_vk></lc-h></vk-k> <tx-s></<_yq><b6_><_ac> <q7_> i </x9_> </t1_></<i0_> i </m8_></_jq></<q5_><o1_> p </_fz></<_zs> e </_qv></j8_></pi-v></ka-g> <ue-p></<_uq> c </q2_></_fy> <n4_> 4zjp </h1_> <e1_> <_zm> <!-- v --> </_qu> </y7_>