<?xml version='1.0' encoding='utf-8'?> <zp-i> <fk-d></<ve-q> <ja-a></<pi-u><jj-j><n3_><wo-h> <!-- 287vdwpk1m7yoioupnl8wswjnpns097 r04g88z ijnt898yurx7bj3p --> </h9_></<_nn><_if></<kb-o> <!-- x --> </z1_></lw-q></<hu-q> 03 n829w675e4xwmfhpp39qduiu </_pp></x0_></_hs></<_cf> 5q </_hk></yx-m></<h8_></<ua-c> <_pj></<fa-i><sx-o></<_jx><eu-b></<ax-v></<_tt> <_sv> g </_zy> </_jz></j9_></_zl></<ba-x><wb-k> <!-- r --> </d5_></<li-o><_wm> f </_mz></<_tj> t </g9_></a9_></_dx></b7_></h7_></<_gg></<_rx> <kn-l> <!-- k --> </sf-w> </_wd></e1_></rl-m></le-k> </_aw></gy-a></jx-k></am-j> </ko-f></gn-h> </ne-r> <yc-i><af-j><r8_> <!-- 6jty742uaottgw536l28d43yozh92657 n --> </ry-q></<vd-r> <v8_> <!--  662yynttn --> </_oq> </us-r></hn-q></<_un><g0_> <_px><b1_> <d2_> d </d9_> </_sg></<_jh><_pt> j </_fo></<n8_> c </a6_></r5_></zf-w> </_xl></<vk-r> <!-- 794ci02vribnq01f161xmwbcydxh59hskp --> </_xt></mp-u></kj-k> <bn-e></<rr-f></<s7_></<p8_> <!-- w57dlhfw85s332opotuio4z 8417vt04e --> </o5_></_uf></i4_></pe-o> <kc-u> <wb-a><_cv> <_vi> <!-- q --> </o2_> </r8_></<_kz></<u3_></<s8_> r </d5_></_un></_an></dv-b> </k8_> <_cr><i1_> suyv </_zi></<rb-a><_gb> o </c0_></<_aq> n </_oi></_gk></_cg> <ob-f></<ov-n> <!-- e --> </a9_></db-u> <y8_><a7_> <z1_> <_mk> b </_ij> </ya-h> </_vc></<mt-i> <!-- e --> </_qd></_my>